pdf_signer/__init__.py
pdf_signer/config.py
pdf_signer/core.py
pdf_signer/exceptions.py
pdf_signer/utils.py
pdf_signer-0.1.3.dist-info/LICENSE
pdf_signer-0.1.3.dist-info/METADATA
pdf_signer-0.1.3.dist-info/WHEEL
pdf_signer-0.1.3.dist-info/top_level.txt
pdf_signer-0.1.3.dist-info/RECORD
